{
  "gold_price_oz_usd": 4528.81,
  "gold_price_gram_usd": 145.6,
  "sovereign_value_ils": 3005.63,
  "sovereign_value_usd": 1065.83,
  "sovereign_gold_grams": 7.32,
  "silver_price_oz_usd": 76.3,
  "silver_price_gram_usd": 2.45,
  "half_shekel_9g_ils": 62.26,
  "half_shekel_9g_usd": 22.08,
  "half_shekel_96g_ils": 66.41,
  "half_shekel_96g_usd": 23.55,
  "usd_ils_rate": 2.82,
  "last_updated": "2026-06-02 11:21:26",
  "last_updated_hebrew": "02.06.2026, 11:21",
  "last_updated_timestamp": 1780399286
}